ambition_inmemorystorage-1.4.0.dist-info/DESCRIPTION.rst
ambition_inmemorystorage-1.4.0.dist-info/METADATA
ambition_inmemorystorage-1.4.0.dist-info/metadata.json
ambition_inmemorystorage-1.4.0.dist-info/RECORD
ambition_inmemorystorage-1.4.0.dist-info/top_level.txt
ambition_inmemorystorage-1.4.0.dist-info/WHEEL
ambition_inmemorystorage-1.4.0.dist-info/zip-safe
inmemorystorage/__init__.py
inmemorystorage/storage.py
inmemorystorage/test_settings.py
