Metadata-Version: 2.0
Name: ambition-inmemorystorage
Version: 1.4.0
Summary: A non-persistent in-memory data storage backend for Django.
Home-page: https://github.com/waveaccounting/dj-inmemorystorage
Author: Cody Soyland, Seán Hayes, Tore Birkeland, Nick Presta
Author-email: opensource@waveapps.com
License: Copyright (c) 2013, Cody Soyland, Seán Hayes, Tore Birkeland, Wave Accounting Inc.
Requires-Dist: Django (>=1.4)
Requires-Dist: six (>=1.4.1)
